{
  "AD": ["ca"],
  "AE": ["ar", "en"],
  "AF": ["fa", "ps"],
  "AL": ["sq"],
  "AM": ["hy", "ru"],
  "AO": ["pt"],
  "AQ": ["en"],
  "AR": ["es"],
  "AT": ["de", "en"],
  "AU": ["en"],
  "AZ": ["az", "ru"],

  "BA": ["bs", "hr", "sr"],
  "BD": ["bn"],
  "BE": ["nl", "fr", "en"],
  "BF": ["fr"],
  "BG": ["bg"],
  "BH": ["ar", "en"],
  "BI": ["fr"],
  "BJ": ["fr"],
  "BO": ["es"],
  "BR": ["pt"],
  "BS": ["en"],
  "BT": ["dz"],
  "BW": ["en"],
  "BY": ["be", "ru"],

  "CA": ["en", "fr"],
  "CD": ["fr"],
  "CF": ["fr"],
  "CG": ["fr"],
  "CH": ["de", "fr", "it", "en"],
  "CI": ["fr"],
  "CL": ["es"],
  "CM": ["fr", "en"],
  "CN": ["zh"],
  "CO": ["es"],
  "CR": ["es"],
  "CU": ["es"],
  "CV": ["pt"],
  "CY": ["el", "tr", "en"],
  "CZ": ["cs", "en"],

  "DE": ["de", "en"],
  "DK": ["da", "en"],
  "DO": ["es"],
  "DZ": ["ar", "fr"],

  "EC": ["es"],
  "EE": ["et", "en", "ru"],
  "EG": ["ar"],
  "ES": ["es"],
  "ET": ["am"],

  "FI": ["fi", "sv", "en"],
  "FR": ["fr"],

  "GA": ["fr"],
  "GB": ["en"],
  "GE": ["ka", "ru", "en"],
  "GH": ["en"],
  "GL": ["kl", "da", "en"],
  "GR": ["el"],

  "HK": ["zh", "en"],
  "HN": ["es"],
  "HR": ["hr"],
  "HT": ["fr", "ht"],
  "HU": ["hu"],

  "ID": ["id"],
  "IE": ["en"],
  "IL": ["he", "ar", "ru", "en"],
  "IN": ["hi", "en"],
  "IR": ["fa"],
  "IS": ["is", "en"],
  "IT": ["it"],

  "JM": ["en"],
  "JO": ["ar", "en"],
  "JP": ["ja"],

  "KE": ["en", "sw"],
  "KG": ["ky", "ru"],
  "KH": ["km"],
  "KR": ["ko"],
  "KZ": ["kk", "ru"],

  "LA": ["lo"],
  "LB": ["ar", "en"],
  "LI": ["de", "en"],
  "LK": ["si", "ta", "en"],
  "LT": ["lt", "en", "ru"],
  "LU": ["fr", "de", "en"],
  "LV": ["lv", "en", "ru"],
  "LY": ["ar"],

  "MA": ["ar", "fr"],
  "MC": ["fr"],
  "MD": ["ro", "ru"],
  "ME": ["sr"],
  "MG": ["fr", "mg"],
  "MK": ["mk"],
  "ML": ["fr"],
  "MM": ["my"],
  "MO": ["zh", "pt", "en"],
  "MT": ["mt", "en"],
  "MX": ["es"],
  "MY": ["ms", "en"],
  "MZ": ["pt"],

  "NG": ["en"],
  "NL": ["nl", "en"],
  "NO": ["no", "en"],
  "NP": ["ne"],
  "NZ": ["en", "mi"],

  "OM": ["ar", "en"],

  "PA": ["es"],
  "PE": ["es"],
  "PH": ["en", "tl"],
  "PK": ["ur", "en"],
  "PL": ["pl"],
  "PR": ["es", "en"],
  "PT": ["pt"],
  "PY": ["es", "gn"],

  "QA": ["ar", "en"],

  "RO": ["ro"],
  "RS": ["sr"],
  "RU": ["ru"],
  "RW": ["rw", "en"],

  "SA": ["ar", "en"],
  "SD": ["ar"],
  "SE": ["sv", "en"],
  "SG": ["en", "zh", "ms", "ta"],
  "SI": ["sl"],
  "SK": ["sk", "en"],
  "SN": ["fr"],
  "SS": ["en"],
  "SV": ["es"],
  "SY": ["ar"],

  "TH": ["th"],
  "TJ": ["tg", "ru"],
  "TM": ["tk", "ru"],
  "TN": ["ar", "fr"],
  "TR": ["tr"],
  "TW": ["zh"],
  "TZ": ["sw", "en"],

  "UA": ["uk", "ru"],
  "UG": ["en", "sw"],
  "US": ["en", "es"],
  "UY": ["es"],
  "UZ": ["uz", "ru"],

  "VA": ["it", "la", "en"],
  "VE": ["es"],
  "VN": ["vi"],

  "YE": ["ar"],

  "ZA": ["en", "af", "zu"],
  "ZM": ["en"],
  "ZW": ["en", "sn"]
}
