{
	"AF": { "fa": "\u0627\u0641\u063A\u0627\u0646\u0633\u062A\u0627\u0646" },
	"AX": { "sv": "\u00C5land" },
	"AL": { "sq": "Shqip\u00EBria" },
	"AQ": { "la": "Antarctica" },
	"DZ": { "ar": "\u0627\u0644\u062C\u0632\u0627\u0626\u0631" },
	"AS": { "sm": "Amerika S\u0101moa" },
	"AD": { "ca": "Andorra" },
	"AO": { "pt": "Angola" },
	"AI": { "en": "Anguilla" },
	"AG": { "en": "Antigua and Barbuda" },
	"AR": { "es": "Argentina" },
	"AM": { "hy": "\u0540\u0561\u0575\u0561\u057D\u057F\u0561\u0576" },
	"AW": { "nl": "Aruba" },
	"AU": { "en": "Australia" },
	"AT": { "de": "\u00D6sterreich" },
	"AZ": { "az": "Az\u0259rbaycan" },
	"BS": { "en": "The Bahamas" },
	"BH": { "ar": "\u0627\u0644\u0628\u062D\u0631\u064A\u0646" },
	"BD": { "bn": "\u09AC\u09BE\u0982\u09B2\u09BE\u09A6\u09C7\u09B6" },
	"BB": { "en": "Barbados" },
	"BY": { "be": "\u0411\u0435\u043B\u0430\u0440\u0443\u0441\u044C" },
	"BE": {
		"nl": "Belgi\u00EB",
		"fr": "Belgique",
		"de": "Belgien"
	},
	"BZ": { "en": "Belize" },
	"BJ": { "fr": "B\u00E9nin" },
	"BM": { "en": "Bermuda" },
	"BT": { "dz": "\u0F60\u0F56\u0FB4\u0F74\u0F42\u0F0B\u0F61\u0F74\u0F63" },
	"BO": { "es": "Bolivia" },
	"BQ": { "nl": "Bonaire" },
	"BA": { "bs": "Bosna i Hercegovina" },
	"BW": { "en": "Botswana" },
	"BV": { "no": "Bouvet\u00F8ya" },
	"BR": { "pt": "Brasil" },
	"IO": { "en": "British Indian Ocean Territory" },
	"VG": { "en": "British Virgin Islands" },
	"BN": { "ms": "Brunei Darussalam" },
	"BG": { "bg": "\u0411\u044A\u043B\u0433\u0430\u0440\u0438\u044F" },
	"BF": { "fr": "Burkina Faso" },
	"BI": { "rn": "Uburundi" },
	"KH": { "km": "\u1780\u1798\u17D2\u1796\u17BB\u1787\u17B6" },
	"CM": { "fr": "Cameroun" },
	"CA": {
		"en": "Canada",
		"fr": "Canada"
	},
	"CV": { "pt": "Cabo Verde" },
	"KY": { "en": "Cayman Islands" },
	"CF": { "fr": "R\u00E9publique centrafricaine" },
	"TD": { "fr": "Tchad" },
	"CL": { "es": "Chile" },
	"CN": { "zh": "\u4E2D\u56FD" },
	"CX": { "en": "Christmas Island" },
	"CC": { "en": "Cocos (Keeling) Islands" },
	"CO": { "es": "Colombia" },
	"KM": { "ar": "\u062C\u0632\u0631 \u0627\u0644\u0642\u0645\u0631" },
	"CG": { "fr": "Congo" },
	"CD": { "fr": "R\u00E9publique d\u00E9mocratique du Congo" },
	"CK": { "rar": "K\u016Bki '\u0100irani" },
	"CR": { "es": "Costa Rica" },
	"HR": { "hr": "Hrvatska" },
	"CU": { "es": "Cuba" },
	"CW": { "pap": "K\u00F2rsou" },
	"CY": { "el": "\u039A\u03CD\u03C0\u03C1\u03BF\u03C2" },
	"CZ": { "cs": "\u010Cesko" },
	"DK": { "da": "Danmark" },
	"DJ": { "fr": "Djibouti" },
	"DM": { "en": "Dominica" },
	"DO": { "es": "Rep\u00FAblica Dominicana" },
	"TL": { "pt": "Timor-Leste" },
	"EC": { "es": "Ecuador" },
	"EG": { "ar": "\u0645\u0635\u0631" },
	"SV": { "es": "El Salvador" },
	"GQ": { "es": "Guinea Ecuatorial" },
	"ER": { "ti": "\u12A4\u122D\u1275\u122B" },
	"EE": { "et": "Eesti" },
	"SZ": { "ss": "eSwatini" },
	"ET": { "am": "\u12A2\u1275\u12EE\u1335\u12EB" },
	"FK": { "en": "Falkland Islands" },
	"FO": { "fo": "F\u00F8royar" },
	"FJ": { "en": "Fiji" },
	"FI": { "fi": "Suomi" },
	"FR": { "fr": "France" },
	"GF": { "fr": "Guyane fran\u00E7aise" },
	"FM": { "en": "Micronesia" },
	"PF": { "fr": "Polyn\u00E9sie fran\u00E7aise" },
	"TF": { "fr": "Terres australes fran\u00E7aises" },
	"GA": { "fr": "Gabon" },
	"GM": { "en": "The Gambia" },
	"GE": { "ka": "\u10E1\u10D0\u10E5\u10D0\u10E0\u10D7\u10D5\u10D4\u10DA\u10DD" },
	"DE": { "de": "Deutschland" },
	"GH": { "en": "Ghana" },
	"GI": { "en": "Gibraltar" },
	"GR": { "el": "\u0395\u03BB\u03BB\u03AC\u03B4\u03B1" },
	"GL": { "kl": "Kalaallit Nunaat" },
	"GD": { "en": "Grenada" },
	"GP": { "fr": "Guadeloupe" },
	"GU": { "en": "Guam" },
	"GT": { "es": "Guatemala" },
	"GG": { "en": "Guernsey" },
	"GN": { "fr": "Guin\u00E9e" },
	"GW": { "pt": "Guin\u00E9-Bissau" },
	"GY": { "en": "Guyana" },
	"HT": { "ht": "Ayiti" },
	"HM": { "en": "Heard Island and McDonald Islands" },
	"HN": { "es": "Honduras" },
	"HK": { "zh": "\u9999\u6E2F" },
	"HU": { "hu": "Magyarorsz\u00E1g" },
	"IS": { "is": "\u00CDsland" },
	"IN": { "hi": "\u092D\u093E\u0930\u0924" },
	"ID": { "id": "Indonesia" },
	"IR": { "fa": "\u0627\u06CC\u0631\u0627\u0646" },
	"IQ": { "ar": "\u0627\u0644\u0639\u0631\u0627\u0642" },
	"IE": { "ga": "\u00C9ire" },
	"IM": { "en": "Isle of Man" },
	"IL": { "he": "\u05D9\u05E9\u05E8\u05D0\u05DC" },
	"IT": { "it": "Italia" },
	"CI": { "fr": "C\u00F4te d'Ivoire" },
	"JM": { "en": "Jamaica" },
	"JP": { "ja": "\u65E5\u672C" },
	"JE": { "en": "Jersey" },
	"JO": { "ar": "\u0627\u0644\u0623\u0631\u062F\u0646" },
	"KZ": { "kk": "\u049A\u0430\u0437\u0430\u049B\u0441\u0442\u0430\u043D" },
	"KE": { "sw": "Kenya" },
	"KI": { "en": "Kiribati" },
	"KW": { "ar": "\u0627\u0644\u0643\u0648\u064A\u062A" },
	"KG": { "ky": "\u041A\u044B\u0440\u0433\u044B\u0437\u0441\u0442\u0430\u043D" },
	"LA": { "lo": "\u0EA5\u0EB2\u0EA7" },
	"LV": { "lv": "Latvija" },
	"LB": { "ar": "\u0644\u0628\u0646\u0627\u0646" },
	"LS": { "en": "Lesotho" },
	"LR": { "en": "Liberia" },
	"LY": { "ar": "\u0644\u064A\u0628\u064A\u0627" },
	"LI": { "de": "Liechtenstein" },
	"LT": { "lt": "Lietuva" },
	"LU": { "lb": "L\u00EBtzebuerg" },
	"MO": { "zh": "\u6FB3\u9580" },
	"MG": { "mg": "Madagasikara" },
	"MW": { "en": "Malawi" },
	"MY": { "ms": "Malaysia" },
	"MV": { "dv": "\u078B\u07AC\u0788\u07AC\u0780\u07A8" },
	"ML": { "fr": "Mali" },
	"MT": { "mt": "Malta" },
	"MH": { "en": "Marshall Islands" },
	"MQ": { "fr": "Martinique" },
	"MR": { "ar": "\u0645\u0648\u0631\u064A\u062A\u0627\u0646\u064A\u0627" },
	"MU": { "en": "Mauritius" },
	"YT": { "fr": "Mayotte" },
	"MX": { "es": "M\u00E9xico" },
	"MD": { "ro": "Republica Moldova" },
	"MC": { "fr": "Monaco" },
	"MN": { "mn": "\u041C\u043E\u043D\u0433\u043E\u043B \u0423\u043B\u0441" },
	"ME": { "sr": "\u0426\u0440\u043D\u0430 \u0413\u043E\u0440\u0430" },
	"MS": { "en": "Montserrat" },
	"MA": { "ar": "\u0627\u0644\u0645\u063A\u0631\u0628" },
	"MZ": { "pt": "Mo\u00E7ambique" },
	"MM": { "my": "\u1019\u103C\u1014\u103A\u1019\u102C" },
	"NA": { "en": "Namibia" },
	"NR": { "na": "Naoero" },
	"NP": { "ne": "\u0928\u0947\u092A\u093E\u0932" },
	"NL": { "nl": "Nederland" },
	"NC": { "fr": "Nouvelle-Cal\u00E9donie" },
	"NZ": { "mi": "Aotearoa" },
	"NI": { "es": "Nicaragua" },
	"NE": { "fr": "Niger" },
	"NG": { "en": "Nigeria" },
	"NU": { "niu": "Niu\u0113" },
	"NF": { "en": "Norfolk Island" },
	"KP": { "ko": "\uC870\uC120\uBBFC\uC8FC\uC8FD\uC758\uC778\uBBFC\uACF5\uD654\uAD6D" },
	"MK": { "mk": "\u0421\u0435\u0432\u0435\u0440\u043D\u0430 \u041C\u0430\u043A\u0435\u0434\u043E\u043D\u0438\u0458\u0430" },
	"MP": { "en": "Northern Mariana Islands" },
	"NO": { "no": "Norge" },
	"OM": { "ar": "\u0639\u064F\u0645\u0627\u0646" },
	"PK": { "ur": "\u067E\u0627\u06A9\u0633\u062A\u0627\u0646" },
	"PW": { "pau": "Belau" },
	"PS": { "ar": "\u0641\u0644\u0633\u0637\u064A\u0646" },
	"PA": { "es": "Panam\u00E1" },
	"PG": { "tpi": "Papua Niugini" },
	"PY": { "gn": "Paraguay" },
	"PE": { "es": "Per\u00FA" },
	"PH": { "fil": "Pilipinas" },
	"PN": { "en": "Pitcairn Islands" },
	"PL": { "pl": "Polska" },
	"PT": { "pt": "Portugal" },
	"PR": { "es": "Puerto Rico" },
	"QA": { "ar": "\u0642\u0637\u0631" },
	"RE": { "fr": "La R\u00E9union" },
	"RO": { "ro": "Rom\u00E2nia" },
	"RU": { "ru": "\u0420\u043E\u0441\u0441\u0438\u044F" },
	"RW": { "rw": "Rwanda" },
	"BL": { "fr": "Saint-Barth\u00E9lemy" },
	"SH": { "en": "Saint Helena" },
	"KN": { "en": "Saint Kitts and Nevis" },
	"LC": { "en": "Saint Lucia" },
	"MF": { "fr": "Saint-Martin" },
	"PM": { "fr": "Saint-Pierre-et-Miquelon" },
	"VC": { "en": "Saint Vincent and the Grenadines" },
	"ST": { "pt": "S\u00E3o Tom\u00E9 e Pr\u00EDncipe" },
	"WS": { "sm": "S\u0101moa" },
	"SM": { "it": "San Marino" },
	"SA": { "ar": "\u0627\u0644\u0633\u0639\u0648\u062F\u064A\u0629" },
	"SX": { "nl": "Sint Maarten" },
	"SN": { "fr": "S\u00E9n\u00E9gal" },
	"KR": { "ko": "\uB300\uD55C\uBBFC\uAD6D" },
	"RS": { "sr": "\u0421\u0440\u0431\u0438\u0458\u0430" },
	"SC": { "fr": "Seychelles" },
	"SL": { "en": "Sierra Leone" },
	"SG": { "en": "Singapore" },
	"SK": { "sk": "Slovensko" },
	"SI": { "sl": "Slovenija" },
	"SB": { "en": "Solomon Islands" },
	"SO": { "so": "Soomaaliya" },
	"ZA": {
		"en": "South Africa",
		"af": "Suid-Afrika",
		"zu": "iNingizimu Afrika"
	},
	"GS": { "en": "South Georgia and the South Sandwich Islands" },
	"SS": { "en": "South Sudan" },
	"ES": { "es": "Espa\u00F1a" },
	"LK": { "si": "\u0DC1\u0DCA\u200D\u0DBB\u0DD3 \u0DBD\u0D82\u0D9A\u0DCF" },
	"SD": { "ar": "\u0627\u0644\u0633\u0648\u062F\u0627\u0646" },
	"SR": { "nl": "Suriname" },
	"SJ": { "no": "Svalbard" },
	"SE": { "sv": "Sverige" },
	"CH": {
		"de": "Schweiz",
		"fr": "Suisse",
		"it": "Svizzera",
		"rm": "Svizra"
	},
	"SY": { "ar": "\u0633\u0648\u0631\u064A\u0627" },
	"TW": { "zh": "\u81FA\u7063" },
	"TJ": { "tg": "\u0422\u043E\u04B7\u0438\u043A\u0438\u0441\u0442\u043E\u043D" },
	"TZ": { "sw": "Tanzania" },
	"TH": { "th": "\u0E1B\u0E23\u0E30\u0E40\u0E17\u0E28\u0E44\u0E17\u0E22" },
	"TG": { "fr": "Togo" },
	"TK": { "tkl": "Tokelau" },
	"TO": { "to": "Tonga" },
	"TT": { "en": "Trinidad and Tobago" },
	"TN": { "ar": "\u062A\u0648\u0646\u0633" },
	"TM": { "tk": "T\u00FCrkmenistan" },
	"TR": { "tr": "T\u00FCrkiye" },
	"TC": { "en": "Turks and Caicos Islands" },
	"TV": { "en": "Tuvalu" },
	"UG": { "sw": "Uganda" },
	"UA": { "uk": "\u0423\u043A\u0440\u0430\u0457\u043D\u0430" },
	"AE": { "ar": "\u0627\u0644\u0625\u0645\u0627\u0631\u0627\u062A \u0627\u0644\u0639\u0631\u0628\u064A\u0629 \u0627\u0644\u0645\u062A\u062D\u062F\u0629" },
	"GB": { "en": "United Kingdom" },
	"US": { "en": "United States" },
	"UM": { "en": "United States Minor Outlying Islands" },
	"UY": { "es": "Uruguay" },
	"VI": { "en": "United States Virgin Islands" },
	"UZ": { "uz": "O\u02BBzbekiston" },
	"VA": { "la": "Vaticano" },
	"VU": { "bi": "Vanuatu" },
	"VE": { "es": "Venezuela" },
	"VN": { "vi": "Vi\u1EC7t Nam" },
	"WF": { "fr": "Wallis-et-Futuna" },
	"EH": { "ar": "\u0627\u0644\u0635\u062D\u0631\u0627\u0621 \u0627\u0644\u063A\u0631\u0628\u064A\u0629" },
	"YE": { "ar": "\u0627\u0644\u064A\u0645\u0646" },
	"ZM": { "en": "Zambia" },
	"ZW": { "en": "Zimbabwe" }
}